mmgen/__init__.py
mmgen/version.py
mmgen/apis/__init__.py
mmgen/apis/inference.py
mmgen/apis/train.py
mmgen/core/__init__.py
mmgen/core/ddp_wrapper.py
mmgen/core/registry.py
mmgen/core/evaluation/__init__.py
mmgen/core/evaluation/eval_hooks.py
mmgen/core/evaluation/evaluation.py
mmgen/core/evaluation/metric_utils.py
mmgen/core/evaluation/metrics.py
mmgen/core/hooks/__init__.py
mmgen/core/hooks/ceph_hooks.py
mmgen/core/hooks/ema_hook.py
mmgen/core/hooks/pggan_fetch_data_hook.py
mmgen/core/hooks/pickle_data_hook.py
mmgen/core/hooks/visualization.py
mmgen/core/hooks/visualize_training_samples.py
mmgen/core/optimizer/__init__.py
mmgen/core/optimizer/builder.py
mmgen/core/runners/__init__.py
mmgen/core/runners/apex_amp_utils.py
mmgen/core/runners/checkpoint.py
mmgen/core/runners/dynamic_iterbased_runner.py
mmgen/core/runners/fp16_utils.py
mmgen/core/scheduler/__init__.py
mmgen/core/scheduler/lr_updater.py
mmgen/datasets/__init__.py
mmgen/datasets/builder.py
mmgen/datasets/dataset_wrappers.py
mmgen/datasets/grow_scale_image_dataset.py
mmgen/datasets/paired_image_dataset.py
mmgen/datasets/quick_test_dataset.py
mmgen/datasets/singan_dataset.py
mmgen/datasets/unconditional_image_dataset.py
mmgen/datasets/unpaired_image_dataset.py
mmgen/datasets/pipelines/__init__.py
mmgen/datasets/pipelines/augmentation.py
mmgen/datasets/pipelines/compose.py
mmgen/datasets/pipelines/crop.py
mmgen/datasets/pipelines/formatting.py
mmgen/datasets/pipelines/loading.py
mmgen/datasets/pipelines/normalize.py
mmgen/datasets/samplers/__init__.py
mmgen/datasets/samplers/distributed_sampler.py
mmgen/models/__init__.py
mmgen/models/builder.py
mmgen/models/misc.py
mmgen/models/architectures/__init__.py
mmgen/models/architectures/common.py
mmgen/models/architectures/fid_inception.py
mmgen/models/architectures/positional_encoding.py
mmgen/models/architectures/arcface/__init__.py
mmgen/models/architectures/arcface/helpers.py
mmgen/models/architectures/arcface/id_loss.py
mmgen-0.7.1.dist-info/LICENSE
mmgen-0.7.1.dist-info/LICENSES.md
mmgen-0.7.1.dist-info/METADATA
mmgen-0.7.1.dist-info/WHEEL
mmgen-0.7.1.dist-info/top_level.txt
mmgen-0.7.1.dist-info/RECORD
