Metadata-Version: 2.1
Name: mmgen
Version: 0.7.1
Summary: MMGeneration
Home-page: https://github.com/open-mmlab/mmgen
Author: MMGeneration Contributors
Author-email: openmmlab@gmail.com
License: Apache License 2.0
Platform: UNKNOWN
Classifier: Development Status :: 4 - Beta
Classifier: License :: OSI Approved :: Apache Software License
Classifier: Operating System :: OS Independent
Classifier: Programming Language :: Python :: 3
Classifier: Programming Language :: Python :: 3.6
Classifier: Programming Language :: Python :: 3.7
Classifier: Programming Language :: Python :: 3.8
Classifier: Programming Language :: Python :: 3.9
Requires-Dist: mmcls (==0.18.0)
Requires-Dist: ninja
Requires-Dist: numpy
Requires-Dist: prettytable
Requires-Dist: scikit-image
Requires-Dist: scipy
Requires-Dist: tqdm
Requires-Dist: yapf
Requires-Dist: codecov
Requires-Dist: flake8
Requires-Dist: interrogate
Requires-Dist: isort (==4.3.21)
Requires-Dist: pytest
Requires-Dist: pytest-runner
